purecpp_extract/RagPUREAI_extract.cpython-311-x86_64-linux-gnu.so
purecpp_extract/__init__.py
purecpp_extract-1.0.4.dist-info/METADATA
purecpp_extract-1.0.4.dist-info/WHEEL
purecpp_extract-1.0.4.dist-info/top_level.txt
purecpp_extract-1.0.4.dist-info/RECORD
